Metadata-Version: 2.1
Name: handwritten-image
Version: 0.1.1
Summary: Convert plain text into the handwritten text
Home-page: https://github.com/xcapt0/handwritten
Author: Vadim Mukhametgareev
Author-email: townhor@mail.ru
License: UNKNOWN
Keywords: handwrite,handwritten
Platform: UNKNOWN
Classifier: Programming Language :: Python
Classifier: Programming Language :: Python :: 3.5
Classifier: Programming Language :: Python :: 3.6
Classifier: Programming Language :: Python :: 3.8
Classifier: Programming Language :: Python :: Implementation :: PyPy
Classifier: Intended Audience :: Developers
Classifier: Operating System :: OS Independent
